cdci_causality/__init__.py
cdci_causality/cdci_causality.py
cdci_causality-0.0.2.dist-info/LICENSE
cdci_causality-0.0.2.dist-info/METADATA
cdci_causality-0.0.2.dist-info/WHEEL
cdci_causality-0.0.2.dist-info/top_level.txt
cdci_causality-0.0.2.dist-info/RECORD
