Metadata-Version: 2.1
Name: cdci-causality
Version: 0.0.2
Summary: CDCI - Causality
Home-page: https://github.com/soelmicheletti/cdci-causality
Author: Soel Micheletti
Author-email: msoel@ethz.ch
License: MIT
Keywords: statistics,causality
Classifier: Development Status :: 4 - Beta
Classifier: Intended Audience :: Developers
Classifier: Topic :: Scientific/Engineering :: Artificial Intelligence
Classifier: License :: OSI Approved :: MIT License
Classifier: Programming Language :: Python :: 3.8
License-File: LICENSE
Requires-Dist: data-science-types (>=0.2)
